{"CHAN1": {"vmax": 3.44, "vmin": 3.28, "vpp": 0.24, "vavg": 3.361538, "frequency": null, "pslewrate": null, "nslewrate": null, "vmid": null}, "CHAN2": {"vmax": 2.73, "vmin": 2.52, "vpp": 0.21, "vavg": 2.645267, "frequency": null, "pslewrate": null, "nslewrate": null, "vmid": null}, "CHAN3": {"vmax": -10.728, "vmin": -10.936, "vpp": 0.1999998, "vavg": -10.83444, "frequency": 45454.55, "pslewrate": null, "nslewrate": -1642.784, "vmid": -10.828}, "CHAN4": {"vmax": 0.08, "vmin": -0.09999999, "vpp": 0.18, "vavg": -0.01282608, "frequency": null, "pslewrate": null, "nslewrate": null, "vmid": null}}